google/cloud/datastream/__init__.py
google/cloud/datastream/gapic_version.py
google/cloud/datastream/py.typed
google/cloud/datastream_v1/__init__.py
google/cloud/datastream_v1/gapic_metadata.json
google/cloud/datastream_v1/gapic_version.py
google/cloud/datastream_v1/py.typed
google/cloud/datastream_v1/services/__init__.py
google/cloud/datastream_v1/services/datastream/__init__.py
google/cloud/datastream_v1/services/datastream/async_client.py
google/cloud/datastream_v1/services/datastream/client.py
google/cloud/datastream_v1/services/datastream/pagers.py
google/cloud/datastream_v1/services/datastream/transports/__init__.py
google/cloud/datastream_v1/services/datastream/transports/base.py
google/cloud/datastream_v1/services/datastream/transports/grpc.py
google/cloud/datastream_v1/services/datastream/transports/grpc_asyncio.py
google/cloud/datastream_v1/services/datastream/transports/rest.py
google/cloud/datastream_v1/services/datastream/transports/rest_base.py
google/cloud/datastream_v1/types/__init__.py
google/cloud/datastream_v1/types/datastream.py
google/cloud/datastream_v1/types/datastream_resources.py
google/cloud/datastream_v1alpha1/__init__.py
google/cloud/datastream_v1alpha1/gapic_metadata.json
google/cloud/datastream_v1alpha1/gapic_version.py
google/cloud/datastream_v1alpha1/py.typed
google/cloud/datastream_v1alpha1/services/__init__.py
google/cloud/datastream_v1alpha1/services/datastream/__init__.py
google/cloud/datastream_v1alpha1/services/datastream/async_client.py
google/cloud/datastream_v1alpha1/services/datastream/client.py
google/cloud/datastream_v1alpha1/services/datastream/pagers.py
google/cloud/datastream_v1alpha1/services/datastream/transports/__init__.py
google/cloud/datastream_v1alpha1/services/datastream/transports/base.py
google/cloud/datastream_v1alpha1/services/datastream/transports/grpc.py
google/cloud/datastream_v1alpha1/services/datastream/transports/grpc_asyncio.py
google/cloud/datastream_v1alpha1/services/datastream/transports/rest.py
google_cloud_datastream-1.16.0.dist-info/licenses/LICENSE
google_cloud_datastream-1.16.0.dist-info/METADATA
google_cloud_datastream-1.16.0.dist-info/WHEEL
google_cloud_datastream-1.16.0.dist-info/top_level.txt
google_cloud_datastream-1.16.0.dist-info/RECORD
